autointerp/__init__.py
autointerp-0.0.0.dist-info/METADATA
autointerp-0.0.0.dist-info/WHEEL
autointerp-0.0.0.dist-info/top_level.txt
autointerp-0.0.0.dist-info/RECORD
