Metadata-Version: 2.4
Name: autointerp
Version: 0.0.0
Summary: Coming soon
Author-email: Marek Masiak <marek.masiak.20@gmail.com>
